toml_fmt_common/__init__.py
toml_fmt_common/py.typed
toml_fmt_common-1.2.0.dist-info/METADATA
toml_fmt_common-1.2.0.dist-info/WHEEL
toml_fmt_common-1.2.0.dist-info/licenses/LICENSE.txt
toml_fmt_common-1.2.0.dist-info/RECORD
