Metadata-Version: 2.4
Name: toml-fmt-common
Version: 1.2.0
Summary: Common logic to the TOML formatter.
Project-URL: Changelog, https://github.com/tox-dev/toml-fmt-common/releases
Project-URL: Documentation, https://github.com/tox-dev/toml-fmt-common#toml-fmt-common
Project-URL: Homepage, https://github.com/tox-dev/toml-fmt-common
Project-URL: Source, https://github.com/tox-dev/toml-fmt-common
Project-URL: Tracker, https://github.com/tox-dev/toml-fmt-common/issues
Maintainer-email: Bernát Gábor <gaborjbernat@gmail.com>
License-Expression: MIT
License-File: LICENSE.txt
Classifier: Development Status :: 5 - Production/Stable
Classifier: Intended Audience :: Developers
Classifier: License :: OSI Approved :: MIT License
Classifier: Operating System :: OS Independent
Classifier: Programming Language :: Python
Classifier: Programming Language :: Python :: 3 :: Only
Classifier: Programming Language :: Python :: 3.10
Classifier: Programming Language :: Python :: 3.11
Classifier: Programming Language :: Python :: 3.12
Classifier: Programming Language :: Python :: 3.13
Classifier: Programming Language :: Python :: 3.14
Classifier: Topic :: Internet
Classifier: Topic :: Software Development :: Libraries
Classifier: Topic :: System
Requires-Python: >=3.10
Requires-Dist: tomli>=2.2.1; python_version < '3.11'
